ephyspipe/__init__.py
ephyspipe/behavior.py
ephyspipe/brain.py
ephyspipe/config.py
ephyspipe/tests/__init__.py
ephyspipe/tests/test_behavior.py
ephyspipe/tests/test_brain.py
ephyspipeZB-0.0.2.dist-info/LICENSE
ephyspipeZB-0.0.2.dist-info/METADATA
ephyspipeZB-0.0.2.dist-info/WHEEL
ephyspipeZB-0.0.2.dist-info/top_level.txt
ephyspipeZB-0.0.2.dist-info/RECORD
