Metadata-Version: 2.1
Name: ephyspipeZB
Version: 0.0.2
Summary: AY250 Final project: ephys processing pipeline.
Home-page: https://github.com/zbalewski/friendly-enigma
Author: Zuzanna Balewski
Author-email: balewski@berkeley.edu
License: MIT
Platform: any
Classifier: Development Status :: 2 - Pre-Alpha
Classifier: Intended Audience :: Education
Classifier: License :: OSI Approved :: MIT License
Classifier: Programming Language :: Python
Classifier: Programming Language :: Python :: 3.5
Classifier: Programming Language :: Python :: 3.6
Classifier: Programming Language :: Python :: 3.7
Classifier: Programming Language :: Python :: 3.8
Classifier: Programming Language :: Python :: 3.9
Classifier: Topic :: Scientific/Engineering
Requires-Python: >=3
License-File: LICENSE
Requires-Dist: h5py (==3.6.0)
Requires-Dist: mat73 (==0.59)
Requires-Dist: numpy (==1.21.6)
Requires-Dist: pandas (==1.3.5)
Requires-Dist: python-dateutil (==2.8.2)
Requires-Dist: pytz (==2022.1)
Requires-Dist: scipy (==1.7.3)
Requires-Dist: six (==1.16.0)
